{
  "unversionedId": "gameserver_cloudvslifetime",
  "id": "gameserver_cloudvslifetime",
  "title": "Unterschiede Cloud-Gameserver vs. Lifetime Server von ZAP-Hosting",
  "description": "Informationen zu den Unterschieden zwischen Cloud-Gameserver und Lifetime Servern von ZAP-Hosting - ZAP-Hosting.com Dokumentationen",
  "source": "@site/i18n/de/docusaurus-plugin-content-docs/current/gameserver_cloudvslifetime.md",
  "sourceDirName": ".",
  "slug": "/gameserver_cloudvslifetime",
  "permalink": "/guides/de/docs/gameserver_cloudvslifetime",
  "draft": false,
  "editUrl": "https://github.com/zaphosting/docs/tree/master/docs/gameserver_cloudvslifetime.md",
  "tags": [],
  "version": "current",
  "frontMatter": {
    "id": "gameserver_cloudvslifetime",
    "title": "Unterschiede Cloud-Gameserver vs. Lifetime Server von ZAP-Hosting",
    "description": "Informationen zu den Unterschieden zwischen Cloud-Gameserver und Lifetime Servern von ZAP-Hosting - ZAP-Hosting.com Dokumentationen",
    "sidebar_label": "Cloud vs. Lifetime"
  },
  "sidebar": "gameserverSidebar",
  "next": {
    "title": "Resourcenlimit",
    "permalink": "/guides/de/docs/gameserver_resourcelimit"
  }
}