{
  "unversionedId": "unturned_rocketmod_permissions",
  "id": "unturned_rocketmod_permissions",
  "title": "Adjusting server permissions",
  "description": "Information on how to customise the permissions for your Unturned Rocketmod server from ZAP-Hosting - ZAP-Hosting.com documentation",
  "source": "@site/docs/unturned_rocketmod_permissions.md",
  "sourceDirName": ".",
  "slug": "/unturned_rocketmod_permissions",
  "permalink": "/guides/docs/unturned_rocketmod_permissions",
  "draft": false,
  "editUrl": "https://github.com/zaphosting/docs/tree/master/docs/unturned_rocketmod_permissions.md",
  "tags": [],
  "version": "current",
  "frontMatter": {
    "id": "unturned_rocketmod_permissions",
    "title": "Adjusting server permissions",
    "description": "Information on how to customise the permissions for your Unturned Rocketmod server from ZAP-Hosting - ZAP-Hosting.com documentation",
    "sidebar_label": "Adjust Permissions"
  },
  "sidebar": "gameserverSidebar",
  "previous": {
    "title": "Install Plugins",
    "permalink": "/guides/docs/unturned_rocketmod_plugins"
  },
  "next": {
    "title": "Create Caves",
    "permalink": "/guides/docs/dst_create_cave"
  }
}