{
  "unversionedId": "vserver_windows_fs_22",
  "id": "vserver_windows_fs_22",
  "title": "Landwirtschafts-Simulator 2022 auf Windows installieren",
  "description": "Informationen wie du einen Landwirtschafts-Simulator Dedicated Server 2022 auf deinen Windows vServer und Dedicated Server von ZAP-Hosting installieren und einrichten kannst - ZAP-Hosting.com Dokumentationen",
  "source": "@site/i18n/de/docusaurus-plugin-content-docs/current/vserver_windows_fs_22.md",
  "sourceDirName": ".",
  "slug": "/vserver_windows_fs_22",
  "permalink": "/guides/de/docs/vserver_windows_fs_22",
  "draft": false,
  "editUrl": "https://github.com/zaphosting/docs/tree/master/docs/vserver_windows_fs_22.md",
  "tags": [],
  "version": "current",
  "frontMatter": {
    "id": "vserver_windows_fs_22",
    "title": "Landwirtschafts-Simulator 2022 auf Windows installieren",
    "description": "Informationen wie du einen Landwirtschafts-Simulator Dedicated Server 2022 auf deinen Windows vServer und Dedicated Server von ZAP-Hosting installieren und einrichten kannst - ZAP-Hosting.com Dokumentationen",
    "sidebar_label": "Landwirtschafts-Simulator 2022"
  },
  "sidebar": "vpsrootSidebar",
  "previous": {
    "title": "Landwirtschafts-Simulator 2019",
    "permalink": "/guides/de/docs/vserver_windows_fs_19"
  }
}