{
  "unversionedId": "voiceserver_query",
  "id": "voiceserver_query",
  "title": "Query login setup",
  "description": "Information on how to set up a TS query login for your Teamspeak server from ZAP-Hosting - ZAP-Hosting.com documentation",
  "source": "@site/docs/voiceserver_query.md",
  "sourceDirName": ".",
  "slug": "/voiceserver_query",
  "permalink": "/guides/docs/voiceserver_query",
  "draft": false,
  "editUrl": "https://github.com/zaphosting/docs/tree/master/docs/voiceserver_query.md",
  "tags": [],
  "version": "current",
  "frontMatter": {
    "id": "voiceserver_query",
    "title": "Query login setup",
    "description": "Information on how to set up a TS query login for your Teamspeak server from ZAP-Hosting - ZAP-Hosting.com documentation",
    "sidebar_label": "Teamspeak Query Login"
  },
  "sidebar": "voiceserverbotSidebar",
  "previous": {
    "title": "Ts3 Backup",
    "permalink": "/guides/docs/voiceserver_ts3backup"
  }
}